[
  {
    "id": 1,
    "key": "lrALzEBO5Jl7idE",
    "created_at": "2025-08-11T20:30:43Z",
    "duration_days": 1,
    "hwid": null,
    "used_at": null,
    "expires_at": null
  },
  {
    "id": 2,
    "key": "Z3U1LZbM9b8dcXQ",
    "created_at": "2025-08-11T20:30:43Z",
    "duration_days": 1,
    "hwid": null,
    "used_at": null,
    "expires_at": null
  },
  {
    "id": 3,
    "key": "JSvmU0KsqglkPE3",
    "created_at": "2025-08-11T20:30:43Z",
    "duration_days": 1,
    "hwid": null,
    "used_at": null,
    "expires_at": null
  },
  {
    "id": 4,
    "key": "DaUDsD061pilByh",
    "created_at": "2025-08-11T20:30:43Z",
    "duration_days": 1,
    "hwid": null,
    "used_at": null,
    "expires_at": null
  },
  {
    "id": 5,
    "key": "ETyCSWqLHNYH4XE",
    "created_at": "2025-08-11T20:30:43Z",
    "duration_days": 1,
    "hwid": null,
    "used_at": null,
    "expires_at": null
  },
  {
    "id": 6,
    "key": "gdiNyXlN9R1JExC",
    "created_at": "2025-08-11T20:30:43Z",
    "duration_days": 1,
    "hwid": null,
    "used_at": null,
    "expires_at": null
  },
  {
    "id": 7,
    "key": "y5leqHzWK7d7MfI",
    "created_at": "2025-08-11T20:30:43Z",
    "duration_days": 1,
    "hwid": null,
    "used_at": null,
    "expires_at": null
  },
  {
    "id": 8,
    "key": "k52sYOGSidP2xqQ",
    "created_at": "2025-08-11T20:30:43Z",
    "duration_days": 1,
    "hwid": null,
    "used_at": null,
    "expires_at": null
  },
  {
    "id": 9,
    "key": "t4yQTa1aX3IphWi",
    "created_at": "2025-08-11T20:30:43Z",
    "duration_days": 1,
    "hwid": null,
    "used_at": null,
    "expires_at": null
  },
  {
    "id": 10,
    "key": "uIrNVO74MtKWZtW",
    "created_at": "2025-08-11T20:30:43Z",
    "duration_days": 1,
    "hwid": null,
    "used_at": null,
    "expires_at": null
  },
  {
    "id": 11,
    "key": "BfI3MLRZAXOoeh2",
    "created_at": "2025-08-11T20:30:43Z",
    "duration_days": 1,
    "hwid": null,
    "used_at": null,
    "expires_at": null
  },
  {
    "id": 12,
    "key": "8k6HD2kEno5QUXO",
    "created_at": "2025-08-11T20:30:43Z",
    "duration_days": 1,
    "hwid": null,
    "used_at": null,
    "expires_at": null
  },
  {
    "id": 13,
    "key": "KE6o9MoAkGxQF7g",
    "created_at": "2025-08-11T20:30:43Z",
    "duration_days": 1,
    "hwid": null,
    "used_at": null,
    "expires_at": null
  },
  {
    "id": 14,
    "key": "02iOenHSkq7xgyC",
    "created_at": "2025-08-11T20:30:43Z",
    "duration_days": 1,
    "hwid": null,
    "used_at": null,
    "expires_at": null
  },
  {
    "id": 15,
    "key": "FE92GAerxOK3OTf",
    "created_at": "2025-08-11T20:30:43Z",
    "duration_days": 1,
    "hwid": null,
    "used_at": null,
    "expires_at": null
  },
  {
    "id": 16,
    "key": "lzTHDT9fDGrBdKV",
    "created_at": "2025-08-11T20:30:43Z",
    "duration_days": 1,
    "hwid": null,
    "used_at": null,
    "expires_at": null
  },
  {
    "id": 17,
    "key": "ysClPESr0SAyj7P",
    "created_at": "2025-08-11T20:30:43Z",
    "duration_days": 1,
    "hwid": null,
    "used_at": null,
    "expires_at": null
  },
  {
    "id": 18,
    "key": "Nwm9M2aA4A1mXlR",
    "created_at": "2025-08-11T20:30:43Z",
    "duration_days": 1,
    "hwid": null,
    "used_at": null,
    "expires_at": null
  },
  {
    "id": 19,
    "key": "FC0YAqZOZhd6N5U",
    "created_at": "2025-08-11T20:30:43Z",
    "duration_days": 1,
    "hwid": null,
    "used_at": null,
    "expires_at": null
  },
  {
    "id": 20,
    "key": "zah8Hb4VP7NBDi1",
    "created_at": "2025-08-11T20:30:43Z",
    "duration_days": 1,
    "hwid": null,
    "used_at": null,
    "expires_at": null
  },
  {
    "id": 21,
    "key": "lb3k7snTqdyxFyp",
    "created_at": "2025-08-11T20:30:43Z",
    "duration_days": 1,
    "hwid": null,
    "used_at": null,
    "expires_at": null
  },
  {
    "id": 22,
    "key": "eR9XdZfAwLRnrnd",
    "created_at": "2025-08-11T20:30:43Z",
    "duration_days": 1,
    "hwid": null,
    "used_at": null,
    "expires_at": null
  },
  {
    "id": 23,
    "key": "Kjzi6CIGPWgw452",
    "created_at": "2025-08-11T20:30:43Z",
    "duration_days": 1,
    "hwid": null,
    "used_at": null,
    "expires_at": null
  },
  {
    "id": 24,
    "key": "sendJUXXSUKsIWj",
    "created_at": "2025-08-11T20:30:43Z",
    "duration_days": 1,
    "hwid": null,
    "used_at": null,
    "expires_at": null
  },
  {
    "id": 25,
    "key": "NQbmQ99PKYWzKq5",
    "created_at": "2025-08-11T20:30:43Z",
    "duration_days": 1,
    "hwid": null,
    "used_at": null,
    "expires_at": null
  },
  {
    "id": 26,
    "key": "VywF1yf4U2b8dUi",
    "created_at": "2025-08-11T20:30:43Z",
    "duration_days": 1,
    "hwid": null,
    "used_at": null,
    "expires_at": null
  },
  {
    "id": 27,
    "key": "pU71y5wVQXx0MPa",
    "created_at": "2025-08-11T20:30:43Z",
    "duration_days": 1,
    "hwid": null,
    "used_at": null,
    "expires_at": null
  },
  {
    "id": 28,
    "key": "XlXO34jymxHaevE",
    "created_at": "2025-08-11T20:30:43Z",
    "duration_days": 1,
    "hwid": null,
    "used_at": null,
    "expires_at": null
  },
  {
    "id": 29,
    "key": "d6mXD4PPoRKG3fT",
    "created_at": "2025-08-11T20:30:43Z",
    "duration_days": 1,
    "hwid": null,
    "used_at": null,
    "expires_at": null
  },
  {
    "id": 30,
    "key": "nH6vfGL0D2YuijH",
    "created_at": "2025-08-11T20:30:43Z",
    "duration_days": 1,
    "hwid": null,
    "used_at": null,
    "expires_at": null
  },
  {
    "id": 31,
    "key": "AGcpZOqgrDcfyHm",
    "created_at": "2025-08-11T20:30:43Z",
    "duration_days": 1,
    "hwid": null,
    "used_at": null,
    "expires_at": null
  },
  {
    "id": 32,
    "key": "nyopmH51wsidIF3",
    "created_at": "2025-08-11T20:30:43Z",
    "duration_days": 1,
    "hwid": null,
    "used_at": null,
    "expires_at": null
  },
  {
    "id": 33,
    "key": "fZQ3GKdoYDSjM9U",
    "created_at": "2025-08-11T20:30:43Z",
    "duration_days": 1,
    "hwid": null,
    "used_at": null,
    "expires_at": null
  },
  {
    "id": 34,
    "key": "OfWuqyBEWuJsejl",
    "created_at": "2025-08-11T20:30:43Z",
    "duration_days": 1,
    "hwid": null,
    "used_at": null,
    "expires_at": null
  },
  {
    "id": 35,
    "key": "8GaGvnHtmtEXomn",
    "created_at": "2025-08-11T20:30:43Z",
    "duration_days": 1,
    "hwid": null,
    "used_at": null,
    "expires_at": null
  },
  {
    "id": 36,
    "key": "KbWmVtsKtGfVu9Z",
    "created_at": "2025-08-11T20:30:43Z",
    "duration_days": 1,
    "hwid": null,
    "used_at": null,
    "expires_at": null
  },
  {
    "id": 37,
    "key": "YnOfNLS29vvqM2w",
    "created_at": "2025-08-11T20:30:43Z",
    "duration_days": 1,
    "hwid": null,
    "used_at": null,
    "expires_at": null
  },
  {
    "id": 38,
    "key": "4iuy4f0Yefz3EqD",
    "created_at": "2025-08-11T20:30:43Z",
    "duration_days": 1,
    "hwid": null,
    "used_at": null,
    "expires_at": null
  },
  {
    "id": 39,
    "key": "n2j910bIrNxZiNB",
    "created_at": "2025-08-11T20:30:43Z",
    "duration_days": 1,
    "hwid": null,
    "used_at": null,
    "expires_at": null
  },
  {
    "id": 40,
    "key": "QNVLl3NZH0nCXxr",
    "created_at": "2025-08-11T20:30:43Z",
    "duration_days": 1,
    "hwid": null,
    "used_at": null,
    "expires_at": null
  },
  {
    "id": 41,
    "key": "SSF7K3YBbIbcuG6",
    "created_at": "2025-08-11T20:30:43Z",
    "duration_days": 1,
    "hwid": null,
    "used_at": null,
    "expires_at": null
  },
  {
    "id": 42,
    "key": "paYkcibrVqetVFN",
    "created_at": "2025-08-11T20:30:43Z",
    "duration_days": 1,
    "hwid": null,
    "used_at": null,
    "expires_at": null
  },
  {
    "id": 43,
    "key": "GmYZmVyBIhb8a9J",
    "created_at": "2025-08-11T20:30:43Z",
    "duration_days": 1,
    "hwid": null,
    "used_at": null,
    "expires_at": null
  },
  {
    "id": 44,
    "key": "glp9IUuiCa6pyAm",
    "created_at": "2025-08-11T20:30:43Z",
    "duration_days": 1,
    "hwid": null,
    "used_at": null,
    "expires_at": null
  },
  {
    "id": 45,
    "key": "jgJrRp3B45m2Phh",
    "created_at": "2025-08-11T20:30:43Z",
    "duration_days": 1,
    "hwid": null,
    "used_at": null,
    "expires_at": null
  },
  {
    "id": 46,
    "key": "5uUDNsqeLyPOBxX",
    "created_at": "2025-08-11T20:30:43Z",
    "duration_days": 1,
    "hwid": null,
    "used_at": null,
    "expires_at": null
  },
  {
    "id": 47,
    "key": "9kRLXSaxtjaeEdI",
    "created_at": "2025-08-11T20:30:43Z",
    "duration_days": 1,
    "hwid": null,
    "used_at": null,
    "expires_at": null
  },
  {
    "id": 48,
    "key": "COIjkBrBRsgitSy",
    "created_at": "2025-08-11T20:30:43Z",
    "duration_days": 1,
    "hwid": null,
    "used_at": null,
    "expires_at": null
  },
  {
    "id": 49,
    "key": "KFt3zXitxARg8kx",
    "created_at": "2025-08-11T20:30:43Z",
    "duration_days": 1,
    "hwid": null,
    "used_at": null,
    "expires_at": null
  },
  {
    "id": 50,
    "key": "Y6Z4ZhR2K8aa6VP",
    "created_at": "2025-08-11T20:30:43Z",
    "duration_days": 1,
    "hwid": null,
    "used_at": null,
    "expires_at": null
  },
  {
    "id": 51,
    "key": "DvLrzTfCpxFd5Rz",
    "created_at": "2025-08-11T20:30:43Z",
    "duration_days": 1,
    "hwid": null,
    "used_at": null,
    "expires_at": null
  },
  {
    "id": 52,
    "key": "TN8Igz0CQejy5Yc",
    "created_at": "2025-08-11T20:30:43Z",
    "duration_days": 1,
    "hwid": null,
    "used_at": null,
    "expires_at": null
  },
  {
    "id": 53,
    "key": "WAiT9rY9STKapH4",
    "created_at": "2025-08-11T20:30:43Z",
    "duration_days": 1,
    "hwid": null,
    "used_at": null,
    "expires_at": null
  },
  {
    "id": 54,
    "key": "h3ETHl2nbo49OUX",
    "created_at": "2025-08-11T20:30:43Z",
    "duration_days": 1,
    "hwid": null,
    "used_at": null,
    "expires_at": null
  },
  {
    "id": 55,
    "key": "MmS1uZzqeY2eG7W",
    "created_at": "2025-08-11T20:30:43Z",
    "duration_days": 1,
    "hwid": null,
    "used_at": null,
    "expires_at": null
  },
  {
    "id": 56,
    "key": "ZFMCCgUphxYnBaC",
    "created_at": "2025-08-11T20:30:43Z",
    "duration_days": 1,
    "hwid": null,
    "used_at": null,
    "expires_at": null
  },
  {
    "id": 57,
    "key": "xPpIu0AriXxwzkM",
    "created_at": "2025-08-11T20:30:43Z",
    "duration_days": 1,
    "hwid": null,
    "used_at": null,
    "expires_at": null
  },
  {
    "id": 58,
    "key": "OadXgqQfMp3BJtb",
    "created_at": "2025-08-11T20:30:43Z",
    "duration_days": 1,
    "hwid": null,
    "used_at": null,
    "expires_at": null
  },
  {
    "id": 59,
    "key": "0EI1m7hVlK9u44L",
    "created_at": "2025-08-11T20:30:43Z",
    "duration_days": 1,
    "hwid": null,
    "used_at": null,
    "expires_at": null
  },
  {
    "id": 60,
    "key": "4uI6lbYwAoPsq9S",
    "created_at": "2025-08-11T20:30:43Z",
    "duration_days": 1,
    "hwid": null,
    "used_at": null,
    "expires_at": null
  },
  {
    "id": 61,
    "key": "OAHosGyUU3wHiqP",
    "created_at": "2025-08-11T20:30:43Z",
    "duration_days": 1,
    "hwid": null,
    "used_at": null,
    "expires_at": null
  },
  {
    "id": 62,
    "key": "gGBNj7zLokIK5Aw",
    "created_at": "2025-08-11T20:30:43Z",
    "duration_days": 1,
    "hwid": null,
    "used_at": null,
    "expires_at": null
  },
  {
    "id": 63,
    "key": "M7yc8DUsiALgFXZ",
    "created_at": "2025-08-11T20:30:43Z",
    "duration_days": 1,
    "hwid": null,
    "used_at": null,
    "expires_at": null
  },
  {
    "id": 64,
    "key": "hQdg4lVbnFMTwyd",
    "created_at": "2025-08-11T20:30:43Z",
    "duration_days": 1,
    "hwid": null,
    "used_at": null,
    "expires_at": null
  },
  {
    "id": 65,
    "key": "CGgbQb2T7XnJSE6",
    "created_at": "2025-08-11T20:30:43Z",
    "duration_days": 1,
    "hwid": null,
    "used_at": null,
    "expires_at": null
  },
  {
    "id": 66,
    "key": "7qJvW6sTNxrkPaB",
    "created_at": "2025-08-11T20:30:43Z",
    "duration_days": 1,
    "hwid": null,
    "used_at": null,
    "expires_at": null
  },
  {
    "id": 67,
    "key": "59K3ZDknfjx1XdP",
    "created_at": "2025-08-11T20:30:43Z",
    "duration_days": 1,
    "hwid": null,
    "used_at": null,
    "expires_at": null
  },
  {
    "id": 68,
    "key": "7snJmrnZhFK0FLM",
    "created_at": "2025-08-11T20:30:43Z",
    "duration_days": 1,
    "hwid": null,
    "used_at": null,
    "expires_at": null
  },
  {
    "id": 69,
    "key": "dS78xGbWxnO4ldw",
    "created_at": "2025-08-11T20:30:43Z",
    "duration_days": 1,
    "hwid": null,
    "used_at": null,
    "expires_at": null
  },
  {
    "id": 70,
    "key": "3DmduQMOVlFyeHQ",
    "created_at": "2025-08-11T20:30:43Z",
    "duration_days": 1,
    "hwid": null,
    "used_at": null,
    "expires_at": null
  },
  {
    "id": 71,
    "key": "gBs9Amzua75Fkqs",
    "created_at": "2025-08-11T20:30:43Z",
    "duration_days": 1,
    "hwid": null,
    "used_at": null,
    "expires_at": null
  },
  {
    "id": 72,
    "key": "bazrPvghEJQf6WM",
    "created_at": "2025-08-11T20:30:43Z",
    "duration_days": 1,
    "hwid": null,
    "used_at": null,
    "expires_at": null
  },
  {
    "id": 73,
    "key": "yeZ1AN5vCp1Kcm1",
    "created_at": "2025-08-11T20:30:43Z",
    "duration_days": 1,
    "hwid": null,
    "used_at": null,
    "expires_at": null
  },
  {
    "id": 74,
    "key": "dOqLYBPsh7OQq4l",
    "created_at": "2025-08-11T20:30:43Z",
    "duration_days": 1,
    "hwid": null,
    "used_at": null,
    "expires_at": null
  },
  {
    "id": 75,
    "key": "SIXrAuXnHvaZxRF",
    "created_at": "2025-08-11T20:30:43Z",
    "duration_days": 1,
    "hwid": null,
    "used_at": null,
    "expires_at": null
  },
  {
    "id": 76,
    "key": "8PHUl5PKTCYQGQY",
    "created_at": "2025-08-11T20:30:43Z",
    "duration_days": 1,
    "hwid": null,
    "used_at": null,
    "expires_at": null
  },
  {
    "id": 77,
    "key": "1Fz3NOkeOSK7ovQ",
    "created_at": "2025-08-11T20:30:43Z",
    "duration_days": 1,
    "hwid": null,
    "used_at": null,
    "expires_at": null
  },
  {
    "id": 78,
    "key": "FdUL24Hm7GmgdnQ",
    "created_at": "2025-08-11T20:30:43Z",
    "duration_days": 1,
    "hwid": null,
    "used_at": null,
    "expires_at": null
  },
  {
    "id": 79,
    "key": "UQww7vAeFLy7y7v",
    "created_at": "2025-08-11T20:30:43Z",
    "duration_days": 1,
    "hwid": null,
    "used_at": null,
    "expires_at": null
  },
  {
    "id": 80,
    "key": "nAdL96hv8cbWcIe",
    "created_at": "2025-08-11T20:30:43Z",
    "duration_days": 1,
    "hwid": null,
    "used_at": null,
    "expires_at": null
  },
  {
    "id": 81,
    "key": "IPCKjAhvtv5MndI",
    "created_at": "2025-08-11T20:30:43Z",
    "duration_days": 1,
    "hwid": null,
    "used_at": null,
    "expires_at": null
  },
  {
    "id": 82,
    "key": "Z8tctB8dFH9cyok",
    "created_at": "2025-08-11T20:30:43Z",
    "duration_days": 1,
    "hwid": null,
    "used_at": null,
    "expires_at": null
  },
  {
    "id": 83,
    "key": "0lOa5wrXXEikkRM",
    "created_at": "2025-08-11T20:30:43Z",
    "duration_days": 1,
    "hwid": null,
    "used_at": null,
    "expires_at": null
  },
  {
    "id": 84,
    "key": "ISM6JA6okGfVlfx",
    "created_at": "2025-08-11T20:30:43Z",
    "duration_days": 1,
    "hwid": null,
    "used_at": null,
    "expires_at": null
  },
  {
    "id": 85,
    "key": "5PerHVbLFriTa9s",
    "created_at": "2025-08-11T20:30:43Z",
    "duration_days": 1,
    "hwid": null,
    "used_at": null,
    "expires_at": null
  },
  {
    "id": 86,
    "key": "U0FKUnDLsNvh508",
    "created_at": "2025-08-11T20:30:43Z",
    "duration_days": 1,
    "hwid": null,
    "used_at": null,
    "expires_at": null
  },
  {
    "id": 87,
    "key": "3YIBgJMUuE8NuC6",
    "created_at": "2025-08-11T20:30:43Z",
    "duration_days": 1,
    "hwid": null,
    "used_at": null,
    "expires_at": null
  },
  {
    "id": 88,
    "key": "lkCPMFJRcTIhkpf",
    "created_at": "2025-08-11T20:30:43Z",
    "duration_days": 1,
    "hwid": null,
    "used_at": null,
    "expires_at": null
  },
  {
    "id": 89,
    "key": "hmylzZ8eqzA6Zop",
    "created_at": "2025-08-11T20:30:43Z",
    "duration_days": 1,
    "hwid": null,
    "used_at": null,
    "expires_at": null
  },
  {
    "id": 90,
    "key": "yar6ZXtzgTSVM1K",
    "created_at": "2025-08-11T20:30:43Z",
    "duration_days": 1,
    "hwid": null,
    "used_at": null,
    "expires_at": null
  },
  {
    "id": 91,
    "key": "PtUScTaf2UsCCgk",
    "created_at": "2025-08-11T20:30:43Z",
    "duration_days": 1,
    "hwid": null,
    "used_at": null,
    "expires_at": null
  },
  {
    "id": 92,
    "key": "6kte5FTyEa2Acew",
    "created_at": "2025-08-11T20:30:43Z",
    "duration_days": 1,
    "hwid": null,
    "used_at": null,
    "expires_at": null
  },
  {
    "id": 93,
    "key": "oUeBryPTgFzRArd",
    "created_at": "2025-08-11T20:30:43Z",
    "duration_days": 1,
    "hwid": null,
    "used_at": null,
    "expires_at": null
  },
  {
    "id": 94,
    "key": "IjjVaaL0OQxNcU0",
    "created_at": "2025-08-11T20:30:43Z",
    "duration_days": 1,
    "hwid": null,
    "used_at": null,
    "expires_at": null
  },
  {
    "id": 95,
    "key": "fs1uDAuyeGLOFDM",
    "created_at": "2025-08-11T20:30:43Z",
    "duration_days": 1,
    "hwid": null,
    "used_at": null,
    "expires_at": null
  },
  {
    "id": 96,
    "key": "rorMjxLEovLDCaJ",
    "created_at": "2025-08-11T20:30:43Z",
    "duration_days": 1,
    "hwid": null,
    "used_at": null,
    "expires_at": null
  },
  {
    "id": 97,
    "key": "RtKc1upzCmVgV56",
    "created_at": "2025-08-11T20:30:43Z",
    "duration_days": 1,
    "hwid": null,
    "used_at": null,
    "expires_at": null
  },
  {
    "id": 98,
    "key": "1hkzZZ7ptzK9fQD",
    "created_at": "2025-08-11T20:30:43Z",
    "duration_days": 1,
    "hwid": null,
    "used_at": null,
    "expires_at": null
  },
  {
    "id": 99,
    "key": "V7uVDROqxLg4bs2",
    "created_at": "2025-08-11T20:30:43Z",
    "duration_days": 1,
    "hwid": null,
    "used_at": null,
    "expires_at": null
  },
  {
    "id": 100,
    "key": "Au23ci0pGcBR3rN",
    "created_at": "2025-08-11T20:30:43Z",
    "duration_days": 1,
    "hwid": null,
    "used_at": null,
    "expires_at": null
  }
]